setup.py
grsearch/__init__.py
grsearch/grsearch.py
grsearch/tfidf.py
grsearch.egg-info/PKG-INFO
grsearch.egg-info/SOURCES.txt
grsearch.egg-info/dependency_links.txt
grsearch.egg-info/top_level.txt