Metadata-Version: 1.1
Name: grsearch
Version: 0.6
Summary: find keyword within string chars or files.
Home-page: http://github.com/herrersystem/grsearch
Author: herrersystem
Author-email: herrersystem@mailoo.org
License: MIT
Keywords: grammatical search find tf idf
Platform: UNKNOWN
Classifier: Programming Language :: Python :: 2.7
Classifier: Programming Language :: Python :: 3.4
